{
   "_comment": "PPDM Config",
   "ppdmOVALocation": "C:\\Downloads\\dellemc-ppdm-sw-19.14.0-20.ova",
   "ovfToolLocation": "ovftool",
   "ppdmVmName": "PPDM",
   "timeZone": "London",
   "ntpServers": ["10.0.0.2, 10.0.0.3"],
   "dnsServers": ["10.0.0.2, 10.0.0.3"],
   "vcFQDNorIP": "vc.mydomain.com",
   "vcPort": 443,
   "vcUser": "idan@vsphere.local",
   "vcPassword": "MyExamplePwd!",
   "datacenter": "MyDC1",
   "esxCluster": "DC1_HA1",
   "ppdmIpV4": "10.0.0.10",
   "ppdmIpV4Netmask": "255.255.255.0",
   "ppdmIpv4Gateway": "10.0.0.1",
   "ppdmFQDN": "ppdm.mydomain.com",
   "ppdmAdminPwd": "MyExamplePPDMPwd!",
   "ppdmDatastore":"PMAX0123_0010_DS1",
   "ppdmMgmtNetwork": "VM Network",
   "_comment2": "Optionally provide full path to license file, defaults to trial license",
   "licenseFile": "C:\\Downloads\\MyLicense.xml"
}